qa_generator_ru/__init__.py
qa_generator_ru-2025.9.142056.dist-info/licenses/LICENSE
qa_generator_ru-2025.9.142056.dist-info/METADATA
qa_generator_ru-2025.9.142056.dist-info/WHEEL
qa_generator_ru-2025.9.142056.dist-info/top_level.txt
qa_generator_ru-2025.9.142056.dist-info/RECORD
