Metadata-Version: 2.4
Name: qa_generator_ru
Version: 2025.9.142056
Author-email: Eugene Evstafev <hi@eugene.plus>
License: MIT License
Project-URL: Repository, https://pypi.org/project/qa_generator_ru/
Requires-Python: >=3.9
License-File: LICENSE
Dynamic: license-file
